README.md
setup.py
easypost_aiohttp/__init__.py
easypost_aiohttp/importer.py
easypost_aiohttp/version.py
easypost_aiohttp.egg-info/PKG-INFO
easypost_aiohttp.egg-info/SOURCES.txt
easypost_aiohttp.egg-info/dependency_links.txt
easypost_aiohttp.egg-info/requires.txt
easypost_aiohttp.egg-info/top_level.txt