Metadata-Version: 1.0
Name: easypost-aiohttp
Version: 3.4.1
Summary: EasyPost Shipping API Client Library for Python asyncio
Home-page: https://easypost.com/
Author: Jihyuk Bok
Author-email: jhbok@newstore.com
License: UNKNOWN
Platform: UNKNOWN
